langchain_mpt_wrapper/__init__.py
langchain_mpt_wrapper/wrapper.py
langchain_mpt_wrapper-0.0.3.dist-info/METADATA
langchain_mpt_wrapper-0.0.3.dist-info/WHEEL
langchain_mpt_wrapper-0.0.3.dist-info/top_level.txt
langchain_mpt_wrapper-0.0.3.dist-info/RECORD
