Metadata-Version: 2.1
Name: langchain-mpt-wrapper
Version: 0.0.3
Summary: UNKNOWN
Home-page: UNKNOWN
Author: UNKNOWN
Author-email: UNKNOWN
License: UNKNOWN
Platform: UNKNOWN
Requires-Dist: langchain (==0.0.173)
Requires-Dist: torch (==2.0.1)
Requires-Dist: transformers (==4.29.2)
Requires-Dist: sentence-transformers
